{"nodes": [{"id": "c_ai_codebase_vedic_astrology_marriage_marriageastro_main_src_pages_features_synastrypage_tsx", "label": "SynastryPage.tsx", "file_type": "code", "source_file": "C:\\Ai Codebase\\Vedic & Astrology\\Marriage\\MarriageAstro-main\\src\\pages\\features\\SynastryPage.tsx", "source_location": "L1"}], "edges": [{"source": "c_ai_codebase_vedic_astrology_marriage_marriageastro_main_src_pages_features_synastrypage_tsx", "target": "react", "relation": "imports_from", "context": "import", "confidence": "EXTRACTED", "source_file": "C:\\Ai Codebase\\Vedic & Astrology\\Marriage\\MarriageAstro-main\\src\\pages\\features\\SynastryPage.tsx", "source_location": "L8", "weight": 1.0}, {"source": "c_ai_codebase_vedic_astrology_marriage_marriageastro_main_src_pages_features_synastrypage_tsx", "target": "react_router_dom", "relation": "imports_from", "context": "import", "confidence": "EXTRACTED", "source_file": "C:\\Ai Codebase\\Vedic & Astrology\\Marriage\\MarriageAstro-main\\src\\pages\\features\\SynastryPage.tsx", "source_location": "L9", "weight": 1.0}, {"source": "c_ai_codebase_vedic_astrology_marriage_marriageastro_main_src_pages_features_synastrypage_tsx", "target": "lucide_react", "relation": "imports_from", "context": "import", "confidence": "EXTRACTED", "source_file": "C:\\Ai Codebase\\Vedic & Astrology\\Marriage\\MarriageAstro-main\\src\\pages\\features\\SynastryPage.tsx", "source_location": "L10", "weight": 1.0}, {"source": "c_ai_codebase_vedic_astrology_marriage_marriageastro_main_src_pages_features_synastrypage_tsx", "target": "c_ai_codebase_vedic_astrology_marriage_marriageastro_main_src_components_seohead", "relation": "imports_from", "context": "import", "confidence": "EXTRACTED", "source_file": "C:\\Ai Codebase\\Vedic & Astrology\\Marriage\\MarriageAstro-main\\src\\pages\\features\\SynastryPage.tsx", "source_location": "L11", "weight": 1.0}, {"source": "c_ai_codebase_vedic_astrology_marriage_marriageastro_main_src_pages_features_synastrypage_tsx", "target": "components_seohead_seohead", "relation": "imports", "context": "import", "confidence": "EXTRACTED", "source_file": "C:\\Ai Codebase\\Vedic & Astrology\\Marriage\\MarriageAstro-main\\src\\pages\\features\\SynastryPage.tsx", "source_location": "L11", "weight": 1.0}], "raw_calls": []}